AUTHORS
ChangeLog
LICENSE
MANIFEST.in
README
autobuild.sh
gerrymander.spec
gerrymander.spec.in
setup.py
conf/gerrymander.conf-example
gerrymander/__init__.py
gerrymander/client.py
gerrymander/commands.py
gerrymander/format.py
gerrymander/git.py
gerrymander/model.py
gerrymander/operations.py
gerrymander/pager.py
gerrymander/reports.py
gerrymander.egg-info/PKG-INFO
gerrymander.egg-info/SOURCES.txt
gerrymander.egg-info/dependency_links.txt
gerrymander.egg-info/requires.txt
gerrymander.egg-info/top_level.txt
scripts/gerrymander
tests/test_model.py