Metadata-Version: 1.0
Name: gerrymander
Version: 1.5
Summary: A client API and command line tool for gerrit
Home-page: https://github.com/berrange/gerrymander
Author: Daniel P. Berrange
Author-email: dan-gerrymander@berrange.com
License: ASL 2.0
Platform: UNKNOWN
